docs/build/html/.buildinfo
docs/build/html/.nojekyll
docs/build/html/_modules/hifis_surveyval/core/dispatch.html
docs/build/html/_modules/hifis_surveyval/core/preprocess.html
docs/build/html/_modules/hifis_surveyval/core/settings.html
docs/build/html/_modules/hifis_surveyval/core/util.html
docs/build/html/_modules/hifis_surveyval/data_container.html
docs/build/html/_modules/hifis_surveyval/hifis_surveyval.html
docs/build/html/_modules/hifis_surveyval/models/answer_option.html
docs/build/html/_modules/hifis_surveyval/models/mixins/mixins.html
docs/build/html/_modules/hifis_surveyval/models/mixins/uses_settings.html
docs/build/html/_modules/hifis_surveyval/models/mixins/yaml_constructable.html
docs/build/html/_modules/hifis_surveyval/models/question.html
docs/build/html/_modules/hifis_surveyval/models/question_collection.html
docs/build/html/_modules/hifis_surveyval/models/translated.html
docs/build/html/_modules/hifis_surveyval/plotting/matplotlib_color_map_parameters.html
docs/build/html/_modules/hifis_surveyval/plotting/matplotlib_plotter.html
docs/build/html/_modules/hifis_surveyval/plotting/plotter.html
docs/build/html/_modules/hifis_surveyval/plotting/supported_output_format.html
docs/build/html/_modules/hifis_surveyval/printing/printer.html
docs/build/html/_modules/index.html
docs/build/html/_sources/index.rst.txt
docs/build/html/_sources/modules/hifis_surveyval.core.rst.txt
docs/build/html/_sources/modules/hifis_surveyval.models.mixins.rst.txt
docs/build/html/_sources/modules/hifis_surveyval.models.rst.txt
docs/build/html/_sources/modules/hifis_surveyval.plotting.rst.txt
docs/build/html/_sources/modules/hifis_surveyval.printing.rst.txt
docs/build/html/_sources/modules/hifis_surveyval.rst.txt
docs/build/html/_sources/modules/modules.rst.txt
docs/build/html/_sources/pages/accessing_data.rst.txt
docs/build/html/_sources/pages/api.rst.txt
docs/build/html/_sources/pages/development.rst.txt
docs/build/html/_sources/pages/getting_started.rst.txt
hifis_surveyval-1.5.3.dist-info/METADATA
hifis_surveyval-1.5.3.dist-info/entry_points.txt
hifis_surveyval-1.5.3.dist-info/WHEEL
hifis_surveyval-1.5.3.dist-info/LICENSES/GPL-3.0-or-later.txt
hifis_surveyval-1.5.3.dist-info/RECORD
