Metadata-Version: 2.1
Name: hifis-surveyval
Version: 1.5.3
Summary: The HIFIS Surveyval Framework is a tool to analyse survey data from LimeSurvey data exports.
Home-page: https://codebase.helmholtz.cloud/hifis/overall/surveys/hifis-surveyval
License: GPL-3.0-or-later
Author: HIFIS Software
Author-email: software@hifis.net
Requires-Python: >=3.8.1,<3.12
Classifier: Development Status :: 5 - Production/Stable
Classifier: Intended Audience :: Science/Research
Classifier: License :: OSI Approved :: GNU General Public License v3 or later (GPLv3+)
Classifier: Programming Language :: Python :: 3
Classifier: Programming Language :: Python :: 3.9
Classifier: Programming Language :: Python :: 3.10
Classifier: Programming Language :: Python :: 3.11
Classifier: Programming Language :: Python :: 3.10
Classifier: Programming Language :: Python :: 3.11
Classifier: Programming Language :: Python :: 3.8
Classifier: Programming Language :: Python :: 3.9
Classifier: Topic :: Scientific/Engineering
Requires-Dist: click (>=8.0)
Requires-Dist: matplotlib (>=3.2.0)
Requires-Dist: numpy (>=1.18.1)
Requires-Dist: pandas (>=1.3.0)
Requires-Dist: pydantic (>=1.8.1,<2.0.0)
Requires-Dist: python-dotenv (>=0.21.0)
Requires-Dist: pyyaml (>=5.3.1)
Requires-Dist: schema (>=0.7.4,<0.8.0)
Requires-Dist: tabulate (>=0.9.0)
Project-URL: Bug Tracker, https://codebase.helmholtz.cloud/hifis/overall/surveys/hifis-surveyval/-/issues
Project-URL: Changelog, https://codebase.helmholtz.cloud/hifis/overall/surveys/hifis-surveyval/-/blob/main/CHANGELOG.md
Project-URL: CI, https://codebase.helmholtz.cloud/hifis/overall/surveys/hifis-surveyval/-/pipelines
Project-URL: Documentation, https://hifis.pages.hzdr.de/overall/surveys/hifis-surveyval
Project-URL: Repository, https://codebase.helmholtz.cloud/hifis/overall/surveys/hifis-surveyval
